{
  "version": 2,
  "id": "scene-first-agreements",
  "title": "Scene: First Agreements",
  "tags": ["co-parenting", "first-agreements", "negotiation"],

  "actors": {
    "Narrator": {},
    "You": {},
    "Co-Parent": {},
    "Mediator": {}
  },

  "meters": { "trust": 0, "tension": 0, "childStress": 0 },
  "meterOrder": ["trust", "tension", "childStress"],

  "ui": {
    "hud": { "animate": true, "animated": true },
    "dialog": { "defaultSpeaker": "Narrator" }
  },

  "entry": "a1s1",
  "entryNodeId": "a1s1",
  "entryId": "a1s1",
  "entryActId": "act1",
  "start": "a1s1",
  "startNodeId": "a1s1",

  "nodes": [
    {
      "id": "menu",
      "speaker": "Narrator",
      "text": "Main menu placeholder for this scene. Choose “Continue” to start the first agreements conversation.",
      "choices": [
        {
          "id": "menu_c1",
          "label": "Continue",
          "text": "Continue",
          "next": "a1s1",
          "to": "a1s1"
        }
      ]
    },

    {
      "id": "a1s1",
      "entry": true,
      "act": "act1",
      "speaker": "Narrator",
      "title": "Setting the Table",
      "text": "You and your co-parent sit across from each other, not in a courtroom but at a neutral table. The goal today isn’t to win — it’s to find the first few agreements that make everyday life calmer.",
      "tone": "neutral · cautiously hopeful",
      "choices": [
        {
          "id": "a1s1c1",
          "label": "Start with something small and practical.",
          "text": "You suggest starting with school mornings — who does what, and when.",
          "tone": "pragmatic · focused",
          "effects": { "trust": 1, "tension": -1, "childStress": 0 },
          "next": "a1s2",
          "to": "a1s2"
        },
        {
          "id": "a1s1c2",
          "label": "Start by naming how tense things have been.",
          "text": "You say that the last months have been intense for everyone and you’d like less fighting in front of the child.",
          "tone": "vulnerable · direct",
          "effects": { "trust": 0, "tension": 1, "childStress": 0 },
          "next": "a1s2",
          "to": "a1s2"
        }
      ]
    },

    {
      "id": "a1s2",
      "act": "act1",
      "speaker": "Co-Parent",
      "title": "First Reaction",
      "text": "Your co-parent crosses their arms. “Fine. What exactly do you want to change? Because I feel like I’m carrying most of this.”",
      "tone": "defensive · tired",
      "choices": [
        {
          "id": "a1s2c1",
          "label": "Acknowledge their effort before proposing a change.",
          "text": "You start with: “I see how much you’re doing. I don’t want to erase that. I’d like us to write down who does which mornings so we both know where we stand.”",
          "tone": "acknowledging · collaborative",
          "effects": { "trust": 1, "tension": -1, "childStress": 0 },
          "next": "a1s3",
          "to": "a1s3"
        },
        {
          "id": "a1s2c2",
          "label": "Go straight into your complaints.",
          "text": "You reply: “You’re not carrying everything. I’m always adjusting my schedule at the last minute.”",
          "tone": "irritated · sharp",
          "effects": { "trust": -1, "tension": 2, "childStress": 0 },
          "next": "a1s3",
          "to": "a1s3"
        }
      ]
    },

    {
      "id": "a1s3",
      "act": "act1",
      "speaker": "Narrator",
      "title": "Drafting the First Agreement",
      "text": "A draft begins to form: who handles which mornings, when changes must be requested, and how last-minute emergencies are handled.",
      "tone": "structured · practical",
      "choices": [
        {
          "id": "a1s3c1",
          "label": "Put the child’s routine at the center of the agreement.",
          "text": "You ask: “What schedule would feel calmest for our child? Let’s start there and then see what each of us can realistically sustain.”",
          "tone": "child-focused · thoughtful",
          "effects": { "trust": 1, "tension": -1, "childStress": -1 },
          "next": "a1end",
          "to": "a1end"
        },
        {
          "id": "a1s3c2",
          "label": "Focus mostly on what’s convenient for you.",
          "text": "You steer the conversation toward what fits your work and social life best, hoping they’ll adapt.",
          "tone": "self-focused · short-sighted",
          "effects": { "trust": -1, "tension": 1, "childStress": 1 },
          "next": "a1end",
          "to": "a1end"
        }
      ]
    },

    {
      "id": "a1end",
      "act": "act1",
      "speaker": "Narrator",
      "title": "End of Scene – First Agreements",
      "text": "You leave the table with at least one written agreement — imperfect, but real. For the first time in a while, the next school morning doesn’t feel like a cliff edge.",
      "tone": "measured · quietly hopeful",
      "choices": [
        {
          "id": "a1endc1",
          "label": "Return to menu.",
          "text": "Return to the scenario menu.",
          "effects": { "trust": 0, "tension": 0, "childStress": 0 },
          "next": "menu",
          "to": "menu"
        }
      ]
    }
  ],

  "acts": [
    {
      "id": "act1",
      "title": "First Agreements Session",
      "steps": ["a1s1", "a1s2", "a1s3", "a1end"]
    }
  ]
}
